{"cameraMode":{"drawMode":0,"name":"Shaded","section":"Shading Mode"},"sceneLighting":true,"audioPlay":false,"sceneViewState":{"m_AlwaysRefresh":false,"showFog":true,"showSkybox":true,"showFlares":true,"showImageEffects":true,"showParticleSystems":true,"showVisualEffectGraphs":true,"m_FxEnabled":true},"in2DMode":false,"pivot":{"x":-52.4227409362793,"y":-3.5927960872650148,"z":-31.20947265625},"rotation":{"x":-0.21639133989810944,"y":0.7614063620567322,"z":-0.314404159784317,"w":-0.5240338444709778},"size":16.932647705078126,"orthographic":false}